Metadata-Version: 2.1
Name: qimacode
Version: 0.0.1
Summary: 我的第一个python包
Home-page: http://www.dashen.tech
Author: yazguqi
Author-email: 1608049872@qq.com
License: UNKNOWN
Platform: UNKNOWN
Classifier: Programming Language :: Python :: 3
Classifier: License :: OSI Approved :: MIT License
Classifier: Operating System :: OS Independent
